StaticCodeAnalysisHelper/FileScan.py
StaticCodeAnalysisHelper/LanguagesFunctions.py
StaticCodeAnalysisHelper/__init__.py
StaticCodeAnalysisHelper/functions.py
StaticCodeAnalysisHelper/log.py
staticcodeanalysishelper-1.0.0.dist-info/licenses/LICENSE
staticcodeanalysishelper-1.0.0.dist-info/METADATA
staticcodeanalysishelper-1.0.0.dist-info/WHEEL
staticcodeanalysishelper-1.0.0.dist-info/top_level.txt
staticcodeanalysishelper-1.0.0.dist-info/RECORD
