Metadata-Version: 2.4
Name: StaticCodeAnalysisHelper
Version: 1.0.0
Summary: Static Code Analysis Helper helps you perform static code analysis.
Home-page: https://github.com/OsmanKandemir/static-code-analysis-helper.git
Author: OsmanKandemir
Author-email: osmankandemir00@gmail.com
License: GPL-3.0
Keywords: python,SAST,IAST,security-tools
Classifier: Topic :: Software Development :: Build Tools
Classifier: Programming Language :: Python :: 3.10
Classifier: Operating System :: OS Independent
Classifier: Development Status :: 4 - Beta
Classifier: Natural Language :: English
Classifier: Environment :: Console
Classifier: Topic :: Security
Classifier: Typing :: Typed
Classifier: Intended Audience :: Information Technology
Classifier: Intended Audience :: Telecommunications Industry
Classifier: Intended Audience :: System Administrators
Requires-Python: >=3.9
License-File: LICENSE
Dynamic: author
Dynamic: author-email
Dynamic: classifier
Dynamic: description
Dynamic: description-content-type
Dynamic: home-page
Dynamic: keywords
Dynamic: license
Dynamic: license-file
Dynamic: requires-python
Dynamic: summary
